[
    
    
    {
        "url": "/2020/04/28/baumrinden-bestaunen/",
        "title": "Baumrinden bestaunen",
        "content": " \u0026ndash; Im Wald \u0026ndash;   Ich suche die Buche,\nerreiche die Eiche.\nBestaune den Ahorn\nund blühenden Weißdorn.\nDie Kiefer berühren,\nRobinie spüren. \nDie Raupe kann kleben,\nund nach oben streben.\nDie Hornisse dicht,\ndie Stechpalme sticht. \nAls ich nun abbiege,\nsetzt sich eine Fliege\nzu mir auf die Hand,\nwie ein großes Land.\nSie schenkt mir Vertrauen,\num weiter zu bauen. \nAuf Haut wie auf Rinden\nsind Spuren zu finden.\nHat Sturm hier getost,\nspendiere ich Trost.  \n"
    }
    
    , 
    {
        "url": "/post/index.json",
        "title": "Posts",
        "content": ""
    }
    
    , 
    {
        "url": "/2020/04/24/koennen-ketten-retten/",
        "title": "Können Ketten retten?",
        "content": " \u0026ndash; Frei sein \u0026ndash;   Ich bin gefangen,\nwie kam ich rein?\nSchmerzen und Bangen,\nes ist zu klein. \nKetten zerstören,\nlange ringen.\nPlötzlich zu hören,\nVögel singen. \nFliegen und fliegen,\nschwingend und weit.\nNichts kann mich kriegen,\nich bin befreit. \nNach einer Weile\nfühl\u0026rsquo; ich mich leer.\nGlänzen da Teile?\nWo komm\u0026rsquo; ich her? \nTeile der Ketten\nnehme ich auf.\nKönnen sie retten\nden freien Lauf?\n \n"
    }
    
    , 
    {
        "url": "/2020/04/18/wie-verlasse-ich-meine-autobahn/",
        "title": "Wie verlasse ich meine Autobahn?",
        "content": " Gestern spazierte ich mit einer Nachbarin auf einem Waldpfad. Sie fragte mich: \u0026ldquo;Passiert es dir in deiner Ausbildung auch, dass du dir eine Aufgabe nicht zutraust? Und wie gehst du dann vor?\u0026rdquo; - \u0026ldquo;Ja, das kenne ich\u0026rdquo;, antwortete ich. \u0026ldquo;Und ich mache es trotzdem. Einfach tun. Dann ergibt sich ein Weg.\u0026rdquo;\nIn der Ausbildung kommt die Aufgabe von außen. Wie schaffe ich es auch von innen, mich neuen Herausforderungen zu stellen? Das finde ich jetzt in einem Test heraus. Denn auch jetzt bin ich in einer herausvordernden Situation. An diesem Aprilmorgen um 5:45 Uhr singen die Vögel ihr Aufwachlied. Seit einer halben Stunde lese ich Blogartikel von zwei meiner Lieblingsautoren. Doch selbst zu schreiben liegt in weiter Ferne. Verschiedene Stimmen in mir werden laut: \u0026ldquo;Bloggen können andere, nicht ich. Ich möchte endlich Inhalte kreieren, auch wenn es noch am Layout zu arbeiten gibt. Wie teile ich den Text ein? Was interessiert die Leser? Habe ich etwas zu sagen? Ich will etwas Neues schreiben. Gibt es das noch? Das ist zu schwierig für mich.\u0026rdquo; Die abratenden Stimmen entsprechen einer gedanklichen Autobahn. Sie sind so laut, dass ich die hoffnungsvollen kaum höre. Eine Autobahn? Wollte ich nicht über kleine Wege schreiben?\nDreispurige Autobahn Kennst du das? Auf verlässliche Weise wiederholt sich dein Weg durch den Tag. Er scheint durch seine Pflichten starr zu sein. Du fragst dich: \u0026ldquo;Schaffe ich es, alles zu erledigen?\u0026rdquo; Tief in dir flüstert eine Stimme: \u0026ldquo;Da gibt es einen anderen Weg.\u0026rdquo; Sofort wird sie zurechtgewiesen: \u0026ldquo;Dafür ist jetzt keine Zeit. Und überhaupt, das kannst du doch nicht!\u0026rdquo; Oder du überhörst die Stimme sogar ganz.\nNicht nur Stimmen der Gedanken sind in dir. Auch deine Gefühle folgen der starren Spur. Im Zusammenspiel mit den zweifelnden Gedanken ergibt sich eine bestimmte Gefühlsmischung. Wo im Körper spürst du die zweifelnde Gefühlsmischung?\nEbenso folgt dein Tun einer Spur. Die gewohnten Handlungen entsprechen einer dritte Spur. Sie jagt dich mit den verknüpften Gedanken und Gefühlen über Autobahn wie am Vortag.\nDie gedankliche Autobahn verlassen Die dreispurige Autobahn tönt lauter als die flüsternde Stimme. Was können wir tun, um den kaum hörbaren Worten Platz zu geben? Wie verlassen wir die Autobahn?\n Beobachten. Wie ist die Verkehrslage? Augen auf. Wo kommt das Schild zur nächsten Ausfahrt? Autoradio aus. Wie klingt deine innere Stimme? Blinken. Du teilst dein Vorhaben mit. Abbremsen. Die Ausfahrt ist da. Abbiegen. Jetzt bist du auf der Ausfahrt.  Wir stellen fest, dass uns folgende Schritte aus einer gedanklichen Autobahn leiten können:\n Beobachten: die vorhandenen Gedanken, Gefühle und Handlungen beobachten Wahrnehmen: die Ist-Situation wahrnehmen, die fünf Sinne scharf stellen Blinken: anderen und uns selbst mitteilen, dass wir einen anderen Weg nehme Abbremsen und Abbiegen: einen kleinen Schritt in die neue Richtung gehen  In meinem Fall läuft es so ab:\n Ich beobachte meine Gedanken, Gefühle und Handlungen zum Blogschreiben. Z.B. \u0026ldquo;Ich lese Blogartikel. Ich kann sie nicht selbst schreiben.\u0026rdquo; Ich höre die Vögel singen, rieche frische Morgenluft, sehe mein Heft parat liegen. Während die Vögel mir sagen \u0026ldquo;Tu es.\u0026rdquo; spüre ich die Angst es nicht zu schaffen. Außerdem spüre ich die Vorfreude, dass ich es doch schaffen könnte. Und ich beobachte einen alternativen Satz in meinem Kopf: \u0026ldquo;Einfach tun!\u0026rdquo; Ich sage mir: \u0026ldquo;Ich schreibe jetzt.\u0026rdquo; Ich nehme den Stift in die Hand und beginne in mein Heft zu schreiben.  Das Wegzeichen erkennen Die alternativen Gedanken, Gefühle und Handlungen schlummern in uns. Sie dienen uns als Wegzeichen im Prozess. Die folgenden Schritte laufen nicht in einer strengen Reihenfolge ab. Sie geschehen scheinbar ständig und parallel. Die vier Phasen überlappen sich. Bei genauem Hinschauen, kann ich eine tendenzielle Reihenfolge entdecken:\nWahrnehmen - Was ist da?\nWegweiser - Welche kleinen Zeichen sind auch da?\nMitteilen - Wir kommunizieren den Entschluss.\nMachen - Los!\nDie Autobahn rauscht laut neben dem neuen Weg. Verschwinden wird sie nicht. Wir können auf ihr fahren oder sie verlassen. Entschließen wir uns abzubiegen, so erwarten uns Abenteuer. Wie bei meinem Waldspaziergang werden wir uns auf einen Pfad kommen. Wir sehen nur wenige Meter weit und gehen langsam. Denn da hängen Äste über den Weg. Es liegen Steine, über die wir stolpern können. Die Vögel zwitschern und es glänzen da Steine, die wir noch nie gesehen haben. Aus dem kleinen Zeichen wird ein Wegweiser, der uns weiter führt.\nWie sieht deine Autobahn aus? Wie verlässt du sie? Und auf welche Wege kommst du dabei?\n"
    }
    
    , 
    {
        "url": "/2020/04/08/wenn-das-leben-kaum-fliesst/",
        "title": "Wenn das Leben kaum fließt",
        "content": " \u0026ndash; Fließen \u0026ndash;   Wenn das Leben kaum fließt.\nWenn der Regen kaum gießt,\nauf die großen Straßen.\nUnd leider vergaßen\nwir unsere Füße.\nDie blassen Grüße\nwurden schließlich weiß.\nEs ist viel zu heiß.\n\nDer Pfad zu dem Dunkeln,\ndie Warnlichter funkeln.\nZum Weiter entschlossen,\nauch Schatten genossen.\nGanz ohne zu hasten\ndie Wurzeln ertasten.\nBis Farben nun sprießen\nund wir wieder fließen.\n \n"
    }
    
    , 
    {
        "url": "/2020/03/26/das-atelier-entsteht/",
        "title": "Das Atelier entsteht",
        "content": "Die Treppe ist fertig. Das Atelier ist im Entstehen. Hier ein paar Impressionen aus dem Atelier.\n              "
    }
    
    , 
    {
        "url": "/2020/03/24/webseite-mit-hugo-erstellen/",
        "title": "Webseite mit Hugo erstellen",
        "content": " Das ist mein erster Post. Heute ist ein sonniger Märztag mit einer kalten Bise. Wie erstelle ich eine Webseite mit Hugo und Github?\nIch habe mich für eine statische Webseite entschieden. Hier finden wir einen Bericht von Chris über statische Webseiten-Generatoren. Wir benutzen die drei Komponenten Hugo, Windows PowerShell ISE, Visual Studio Code und Github. Chris hat auch einen bebilderten Artikel zum Einstieg in Github-Seiten verfasst.\nEine Hugo-Seite erstellen In der Windows PowerShell erstellen wir den Ordner für die neue Hugo-Seite. In meinem Fall heißt der Ordner \u0026ldquo;blog-lithium\u0026rdquo;:\nmd blog-lithium cd blog-lithium hugo new site ./  Automatisch sind die Ordner archetypes, content, data, layouts, resources, static und themes und die Datei config.toml entstanden. Sie sind typisch für eine Hugo-Webseite. Als zweites passen wir die config.toml an. Die baseURL entspricht dem lokalen Server oder deiner Domain.\nbaseURL = \u0026quot;http://localhost:1313/\u0026quot; languageCode = \u0026quot;de-de\u0026quot; title = \u0026quot;Farbenweg\u0026quot;  Eine leere Seite ist generiert.\nEin Hugo-Theme herunterladen Um ein Theme zu installieren, wechseln wir ins entsprechende Verzeichnis.\ncd themes git clone https://github.com/jrutheiser/hugo-lithium-theme cd ../  Das Theme kann in lithium umbenannt und in der Konfigurationsdatei config.toml als solches festgelegt werden:\nbaseURL = \u0026quot;http://localhost:1313/\u0026quot; languageCode = \u0026quot;de-de\u0026quot; title = \u0026quot;Beispiel Hugo\u0026quot; theme = \u0026quot;lithium\u0026quot;  Dann kopieren wir die Inhalte von ExampleSite in unser Seiten-Verzeichnis.\nEinen Hugo-Inhalt erstellen Um einen ersten Blogeintrag zu erstellen, verwenden wir den Befehl hugo new post/___.md:\nhugo new post/Webseite-mit-Hugo-erstellen.md  Es entsteht im Unterverzeichnis content/post/ eine Seite, in die wir einen Eintrag schreiben können:\n--- title: \u0026quot;Webseite mit Hugo erstellen\u0026quot; date: 2020-03-24T09:51:12+01:00 draft: true --- Das ist mein erster Post. Heute ist ein sonniger Märztag mit einer kalten Bise.  Den Post können wir mit Markdown schreiben. Das ist eine Auszeichungssprache mit guter Lesbarkeit im Vergleich zu HTML. Außerdem fügen wir jetzt ein Bild ein. Wir legen es in das Verzeichnis static/images.\n![Rinde](/images/rinde2.jpg)  Um die Website anzuschauen starten wir\nhugo -D serve  und gehen auf http://localhost:1313/. Die Webseite und das Bild werden angezeigt.\nWebseite auf Domain ziehen Um die Website auf einer Github-Domain anzuzeigen, gehen wir folgendermaßen vor.\nBei der ersten Verwendung des Github-Repositorys klonen wir das Repo in den Public-Ordner:\ngit clone https://github.com/farbenweg/farbenweg.github.io public  Bei den weiteren Änderungen ist das Klonen nicht mehr nötig. Dann genügen die fünf folgenden Zeilen, um Änderungen auf die Domain zu ziehen:\nhugo cd public git add --all git commit -m \u0026quot;inital commit\u0026quot; git push origin master  Um den Post zu sehen, stellen wir im Bereich oberhalb des Post (Front Matter):\ndraft: false  Und in der config.toml wählen wir die neue baseURL:\nbaseURL = \u0026quot;https://farbenweg.github.io/\u0026quot;  Das Über funktioniert Schon seit einiger Zeit fragte ich mich, ob in Hugo deutsche Page-Titel funktionieren. Vor allem für die Über-Seite war es mir wichtig. Die Lösung habe ich heute hier gefunden:\nhttps://discourse.gohugo.io/t/make-url-use-only-ascii-characters/7592\nDas heißt, es braucht nur eine Zeile in der config.toml:\nRemovePathAccents = true  Im Titel ist jetzt ein Über anstelle von Ueber zu sehen! In der URL ist einfach ein u anstelle des ü:\nhttps://farbenweg.github.io/uber.html  Und entsprechend sieht es für den Titel dieses Posts aus.\nNeues Layout Das neue Layout umfasst\n neue Schriftarten,  Merienda für die Titel, Lato für die Texte,  grüne Titel einen höheren und hellgrünen Header, ein größeres Logo im Header, grüne Schrift beim Überfahren der Navigation.  Der Code in /themes/lithium/layouts/partials/head.html für die neue Schriftart lautet:\n\u0026lt;link href='https://fonts.googleapis.com/css?family=Merienda' rel='stylesheet'\u0026gt;  In /themes/lithium/static/css/main.css gab es viele kleine Änderungen für das neue Layout.\nNeu auf Github laden Nach längerem Testen haben sich im Github-Ordner eine Menge angesammelt, die nicht mehr gebraucht werden. Deshalb möchte ich diese Daten löschen. Wenn ich das Theme wechsle, gehe ich ebenfalls so vor, um das Repository ganz zu leeren. Ich wechsle in den Ordner: farbenweg\\blog-lithium\\public [master ≡]\u0026gt;\ngit pull git rm -r . git commit -m \u0026quot;leer\u0026quot; git push  Jetzt ist das Repository leer und ich kann die aktuelle Seite hochladen.\nAuf andere Domain laden Um eine andere Domain zu verwenden, klonen wir das entsprechende Repository in unseren public-Ordner.\ngit clone https://github.com/farbenweg/farbenweg.ch public  Eventuell löschen wir die alte Seite zuerst:\ncd public git rm -r . git commit -m \u0026quot;leer\u0026quot; git push  Dann kompilieren wir die Seite und ziehen sie auf die Domain:\nhugo cd public git add --all git commit -m \u0026quot;inital commit\u0026quot; git push origin master  Jetzt sind alle Dateien auf der Domain. Leider ist nichts im Browser zu sehen. Wir brauchen die wichtige Datei CNAME. Sie enthält den Domainnamen, wenn wir eine beliebige Domain wählen. In meinem Fall steht in der Datei CNAME einfach:\nfarbenweg.ch  Nun funktioniert die Hugo-Seite auf der Domain farbenweg.ch.\nFavicon Jedes Gerät und Betriebssystem verlangt sein eigenes Favicon. Deshalb erstellen wir das Favicon am besten in verschiedenen Grössen und Dateiformaten. Die ganz kleinen Favicons nennen sich favicon.ico oder favicon.png und befinden sich oben im Fenster oder im Tab. Sie sind 16 x 16 Pixel, 32 x 32 Pixel oder 48 x 48 Pixel klein:\nfavicon.ico\nDann gibt es etwas größere Icons, die sich touch-icon.png oder apple-icon.png nennen. Sie werden in den mobilen Browsern verwendet oder in den Favoriten oder Lesezeichen im Browser.\nDa auf meinem alten Smartphone (Samsung Galaxy S4 mini) im Browser das Favicon nicht funktioniert, wird meine Suche nach einer Lösung immer obsessiver. Ich finde immer mehr Größen und Typen von möglichen Favicons für die diversen Geräte und Betriebssysteme.\nDer Code in head.html lautet dann:\n\u0026lt;link rel=\u0026quot;icon\u0026quot; type=\u0026quot;image/ico\u0026quot; sizes=\u0026quot;16x16\u0026quot; href=\u0026quot;/favicon.ico\u0026quot;\u0026gt; \u0026lt;link rel=\u0026quot;icon\u0026quot; type=\u0026quot;image/ico\u0026quot; sizes=\u0026quot;32x32\u0026quot; href=\u0026quot;/favicon.ico\u0026quot;\u0026gt; \u0026lt;link rel=\u0026quot;icon\u0026quot; type=\u0026quot;image/ico\u0026quot; sizes=\u0026quot;64x64\u0026quot; href=\u0026quot;/favicon.ico\u0026quot;\u0026gt; \u0026lt;link rel=\u0026quot;icon\u0026quot; type=\u0026quot;image/png\u0026quot; sizes=\u0026quot;16x16\u0026quot; href=\u0026quot;/favicon-16x16.png\u0026quot;\u0026gt; \u0026lt;link rel=\u0026quot;icon\u0026quot; type=\u0026quot;image/png\u0026quot; sizes=\u0026quot;32x32\u0026quot; href=\u0026quot;/favicon-32x32.png\u0026quot;\u0026gt; \u0026lt;link rel=\u0026quot;icon\u0026quot; type=\u0026quot;image/png\u0026quot; sizes=\u0026quot;96x96\u0026quot; href=\u0026quot;/favicon-96x96.png\u0026quot;\u0026gt; \u0026lt;link rel=\u0026quot;apple-touch-icon-precomposed\u0026quot; sizes=\u0026quot;57x57\u0026quot; href=\u0026quot;/apple-icon-57x57.png\u0026quot;\u0026gt; \u0026lt;link rel=\u0026quot;apple-touch-icon-precomposed\u0026quot; sizes=\u0026quot;60x60\u0026quot; href=\u0026quot;/apple-icon-60x60.png\u0026quot;\u0026gt; \u0026lt;link rel=\u0026quot;apple-touch-icon-precomposed\u0026quot; sizes=\u0026quot;72x72\u0026quot; href=\u0026quot;/apple-icon-72x72.png\u0026quot;\u0026gt; \u0026lt;link rel=\u0026quot;apple-touch-icon-precomposed\u0026quot; sizes=\u0026quot;76x76\u0026quot; href=\u0026quot;/apple-icon-76x76.png\u0026quot;\u0026gt; \u0026lt;link rel=\u0026quot;apple-touch-icon-precomposed\u0026quot; sizes=\u0026quot;114x114\u0026quot; href=\u0026quot;/apple-icon-114x114.png\u0026quot;\u0026gt; \u0026lt;link rel=\u0026quot;apple-touch-icon-precomposed\u0026quot; sizes=\u0026quot;120x120\u0026quot; href=\u0026quot;/apple-icon-120x120.png\u0026quot;\u0026gt; \u0026lt;link rel=\u0026quot;apple-touch-icon-precomposed\u0026quot; sizes=\u0026quot;144x144\u0026quot; href=\u0026quot;/apple-icon-144x144.png\u0026quot;\u0026gt; \u0026lt;link rel=\u0026quot;apple-touch-icon-precomposed\u0026quot; sizes=\u0026quot;152x152\u0026quot; href=\u0026quot;/apple-icon-152x152.png\u0026quot;\u0026gt; \u0026lt;link rel=\u0026quot;apple-touch-icon-precomposed\u0026quot; sizes=\u0026quot;180x180\u0026quot; href=\u0026quot;/apple-icon-180x180.png\u0026quot;\u0026gt; \u0026lt;link rel=\u0026quot;apple-touch-icon-precomposed\u0026quot; sizes=\u0026quot;192x192\u0026quot; href=\u0026quot;/apple-icon-192x192.png\u0026quot;\u0026gt; \u0026lt;link rel=\u0026quot;icon\u0026quot; type=\u0026quot;image/png\u0026quot; sizes=\u0026quot;36x36\u0026quot; href=\u0026quot;/android-icon-36x36.png\u0026quot;\u0026gt; \u0026lt;link rel=\u0026quot;icon\u0026quot; type=\u0026quot;image/png\u0026quot; sizes=\u0026quot;48x48\u0026quot; href=\u0026quot;/android-icon-48x48.png\u0026quot;\u0026gt; \u0026lt;link rel=\u0026quot;icon\u0026quot; type=\u0026quot;image/png\u0026quot; sizes=\u0026quot;72x72\u0026quot; href=\u0026quot;/android-icon-72x72.png\u0026quot;\u0026gt; \u0026lt;link rel=\u0026quot;icon\u0026quot; type=\u0026quot;image/png\u0026quot; sizes=\u0026quot;96x96\u0026quot; href=\u0026quot;/android-icon-96x96.png\u0026quot;\u0026gt; \u0026lt;link rel=\u0026quot;icon\u0026quot; type=\u0026quot;image/png\u0026quot; sizes=\u0026quot;144x144\u0026quot; href=\u0026quot;/android-icon-144x144.png\u0026quot;\u0026gt; \u0026lt;link rel=\u0026quot;icon\u0026quot; type=\u0026quot;image/png\u0026quot; sizes=\u0026quot;192x192\u0026quot; href=\u0026quot;/android-icon-192x192.png\u0026quot;\u0026gt; \u0026lt;link rel=\u0026quot;icon\u0026quot; type=\u0026quot;image/png\u0026quot; sizes=\u0026quot;256x256\u0026quot; href=\u0026quot;/android-icon-256x256.png\u0026quot;\u0026gt; \u0026lt;link rel=\u0026quot;icon\u0026quot; type=\u0026quot;image/png\u0026quot; sizes=\u0026quot;512x512\u0026quot; href=\u0026quot;/android-icon-512x512.png\u0026quot;\u0026gt; \u0026lt;link rel=\u0026quot;manifest\u0026quot; href=\u0026quot;/manifest.json\u0026quot;\u0026gt; \u0026lt;meta name=\u0026quot;msapplication-TileColor\u0026quot; content=\u0026quot;#ffffff\u0026quot;\u0026gt; \u0026lt;meta name=\u0026quot;msapplication-TileImage\u0026quot; content=\u0026quot;/ms-icon-144x144.png\u0026quot;\u0026gt; \u0026lt;meta name=\u0026quot;theme-color\u0026quot; content=\u0026quot;#ffffff\u0026quot;\u0026gt;  Deutsche Umlaute in URLs ersetzen Die deutschen Umlaute in Post-Titeln sollten in der URL richtig ersetzt werden. Beispielsweise möchte ich den Titel \u0026ldquo;Können\u0026rdquo; nicht als /konnen/, sondern als /können/ in der URL. Deshalb verabschiede ich mich in der config.toml wieder vom Akzent-Entfernen, das ich oben eingeführt hatte. Ausserdem führe ich einen Slug anstelle des Titles ein:\n# RemovePathAccents = true [permalinks] # post = \u0026quot;/:year/:month/:day/:title/\u0026quot; post = \u0026quot;/:year/:month/:day/:slug/\u0026quot;  In der Front-Matter des entsprechenden Artikels definieren wir nun neben dem Title auch den Slug:\n--- title: \u0026quot;Können Ketten retten?\u0026quot; slug: /Koennen-Ketten-retten/ date: 2020-04-24T21:56:25+02:00 categories: - Gedichte - Leben tags: - Freiheit - Ketten - Fliegen images: - /images/frei.jpg draft: false ---  Den \u0026ldquo;Ü\u0026rdquo; in der \u0026ldquo;Über\u0026rdquo;-Seite einfach durch ein \u0026ldquo;U\u0026rdquo; zu ersetzen (siehe oben) entspricht nicht der Bedeutung des Wortes\u0026hellip; Es geht ja nicht um ein Taxiunternehmen. Deshalb habe ich in der config.toml auch einen Slug für die Page eingeführt und die URL geändert:\n# RemovePathAccents = true [permalinks] # page = \u0026quot;/:title/\u0026quot; page = \u0026quot;/:slug/\u0026quot; [[menu.main]] name = \u0026quot;Über\u0026quot; url = \u0026quot;/ueber/\u0026quot; weight = 3  In der Front-Matter von Ueber.md steht nun:\n--- title: Über slug: /Ueber/ date: 2020-04-27T08:22:57+00:00 author: Monika Gloor images: - /images/logo.png ---  Ausserdem können wir mit dem Slug den Titel der Search-Seite anpassen:\n--- title: \u0026quot;Suche\u0026quot; slug: /search/ date: 2019-06-07T20:22:57+02:00 disable_comments: true ---  "
    }
    
]